nmfx/__init__.py
nmfx/initialize.py
nmfx/losses.py
nmfx/nmfx.py
nmfx/parameters.py
nmfx/updates.py
nmfx/utils.py
nmfx-0.11.data/scripts/nmfx
nmfx-0.11.data/scripts/nmfx_hdf5
nmfx-0.11.dist-info/LICENSE
nmfx-0.11.dist-info/METADATA
nmfx-0.11.dist-info/WHEEL
nmfx-0.11.dist-info/top_level.txt
nmfx-0.11.dist-info/RECORD
